LICENSE.txt
MANIFEST.in
README.rst
setup.cfg
setup.py
mortgage_calculus/__init__.py
mortgage_calculus/cashflows.py
mortgage_calculus/interest_and_redemption.py
mortgage_calculus.egg-info/PKG-INFO
mortgage_calculus.egg-info/SOURCES.txt
mortgage_calculus.egg-info/dependency_links.txt
mortgage_calculus.egg-info/requires.txt
mortgage_calculus.egg-info/top_level.txt