Metadata-Version: 2.1
Name: mortgage-calculus
Version: 0.0.2
Summary: Tools for the analysis of mortgages
Home-page: http://github.com/ramonVDAKKER/mortgage_calculus
Author: Ramon van den Akker
Author-email: ramon@vandenakker.tech
License: MIT
Keywords: mortgage cashflows annuity interest
Platform: UNKNOWN
Classifier: License :: OSI Approved :: MIT License
Requires-Python: >=3.7
